<?xml version="1.0" encoding="utf-8"?>
<resources>
	<!-- Colors -->
	<!---<color name="primary_text_color">#d0cecb</color>-->
	<color name="primary_text_color">#e0dedb</color>
	<color name="highlight_text_color">#ffffff</color>
	<color name="highlight_color">#bf9d7a</color>
	<color name="primary_background">#445a77</color>

	<dimen name="track_switch_height">24dp</dimen>
	<dimen name="track_switch_width">24dp</dimen>

	<!-- Styles -->
	<style name="BikrTheme" parent="@style/BikrActionBarTheme" />

	<style name="BikrActionBarTheme" parent="@android:style/Theme.Holo">
		<item name="android:actionBarStyle">@style/BikrActionBarStyle</item>
		<item name="android:windowBackground">@drawable/main_bg</item>
		<item name="android:windowActionBarOverlay">true</item>
		<item name="android:windowContentOverlay">@null</item>
		<item name="android:colorForeground">@color/primary_text_color</item>
		<item name="android:textColor">@color/primary_text_color</item>
	</style>

	<style name="BikrActionBarStyle" parent="@android:style/Widget.Holo.Light.ActionBar">
		<item name="android:titleTextStyle">@style/BikrActionBarTitleStyle</item>
		<item name="android:background">@android:color/transparent</item>
		<item name="android:displayOptions">showTitle|showHome|useLogo</item>
		<item name="android:logo">@drawable/icon</item>
	</style>

	<style name="BikrActionBarTitleStyle" parent="@android:style/TextAppearance.Holo.Widget.ActionBar.Title">
		<item name="android:textSize">17sp</item>
		<item name="android:textColor">@color/highlight_color</item>
		<item name="android:textStyle">bold</item>
	</style>

	<style name="BikrSwitchTextAppeance" parent="@android:style/TextAppearance.Holo.Small">
		<item name="android:textColor">@color/primary_text_color</item>
	</style>
</resources>